{"version":2,"kind":"Notebook","sha256":"a780ad9dbdf74ed6803f1ecf48cd1e708ecd4f2cb322bb1d0aac3dbd38a6f1d2","slug":"notebooks.introduction-to-nsdf-openvisus","location":"/notebooks/Introduction_to_NSDF_OpenVISUS.ipynb","dependencies":[],"frontmatter":{"title":"Introduction to NSDF-OpenVISUS","content_includes_title":false,"kernelspec":{"name":"python3","display_name":"Python 3 (ipykernel)","language":"python"},"authors":[{"nameParsed":{"literal":"Aashish Panta","given":"Aashish","family":"Panta"},"name":"Aashish Panta","id":"contributors-myst-generated-uid-0"},{"nameParsed":{"literal":"Amy Gooch","given":"Amy","family":"Gooch"},"name":"Amy Gooch","id":"contributors-myst-generated-uid-1"},{"nameParsed":{"literal":"Giorgio Scorzelli","given":"Giorgio","family":"Scorzelli"},"name":"Giorgio Scorzelli","id":"contributors-myst-generated-uid-2"},{"nameParsed":{"literal":"Valerio Pascucci","given":"Valerio","family":"Pascucci"},"name":"Valerio Pascucci","id":"contributors-myst-generated-uid-3"}],"open_access":true,"license":{"content":{"id":"CC-BY-4.0","url":"https://creativecommons.org/licenses/by/4.0/","name":"Creative Commons Attribution 4.0 International","free":true,"CC":true},"code":{"id":"Apache-2.0","url":"https://opensource.org/licenses/Apache-2.0","name":"Apache License 2.0","free":true,"osi":true}},"github":"https://github.com/ProjectPythia/nsdf-openvisus-cookbook","copyright":"2024","affiliations":[{"id":"UAlbany","name":"University at Albany (SUNY)","department":"Atmospheric and Environmental Sciences","url":"https://www.albany.edu/daes"},{"id":"CISL","name":"NSF National Center for Atmospheric Research","department":"Computational and Information Systems Lab","url":"https://www.cisl.ucar.edu"},{"id":"Unidata","name":"NSF Unidata","url":"https://www.unidata.ucar.edu"},{"id":"Argonne","name":"Argonne National Laboratory","department":"Environmental Science Division","url":"https://www.anl.gov/evs"},{"id":"CarbonPlan","name":"CarbonPlan","url":"https://carbonplan.org"},{"id":"NVIDIA","name":"NVIDIA Corporation","url":"https://www.nvidia.com/"}],"numbering":{"title":{"offset":1}},"source_url":"https://github.com/ProjectPythia/nsdf-openvisus-cookbook/blob/main/notebooks/Introduction_to_NSDF_OpenVISUS.ipynb","edit_url":"https://github.com/ProjectPythia/nsdf-openvisus-cookbook/edit/main/notebooks/Introduction_to_NSDF_OpenVISUS.ipynb","thumbnail":"/nsdf-openvisus-cookbook/build/nsdf-6dc6249214b1413566ceaa595a464d93.png","exports":[{"format":"ipynb","filename":"Introduction_to_NSDF_OpenVISUS.ipynb","url":"/nsdf-openvisus-cookbook/build/Introduction_to_NSDF-d3c3b09702d44e62063a83b2bfae2cd4.ipynb"}]},"widgets":{},"mdast":{"type":"root","children":[{"type":"block","kind":"notebook-content","children":[{"type":"image","url":"/nsdf-openvisus-cookbook/build/nsdf-6dc6249214b1413566ceaa595a464d93.png","alt":"NSDF logo","width":"180px","align":"center","key":"ZaN2hYySB1","urlSource":"../thumbnails/nsdf.png"}],"key":"R8oR8ZoLyE"},{"type":"block","kind":"notebook-content","children":[{"type":"heading","depth":2,"position":{"start":{"line":1,"column":1},"end":{"line":1,"column":1}},"children":[{"type":"text","value":"OpenViSUS: High Performance Big Data Analysis and Visualization","position":{"start":{"line":1,"column":1},"end":{"line":1,"column":1}},"key":"tznLh9xXBh"}],"identifier":"openvisus-high-performance-big-data-analysis-and-visualization","label":"OpenViSUS: High Performance Big Data Analysis and Visualization","html_id":"openvisus-high-performance-big-data-analysis-and-visualization","implicit":true,"key":"koVP6TGiRT"},{"type":"heading","depth":3,"position":{"start":{"line":3,"column":1},"end":{"line":3,"column":1}},"children":[{"type":"text","value":"Overview","position":{"start":{"line":3,"column":1},"end":{"line":3,"column":1}},"key":"ymWZXhqcBt"}],"identifier":"overview","label":"Overview","html_id":"overview","implicit":true,"key":"tvPcVKuFnE"},{"type":"paragraph","position":{"start":{"line":4,"column":1},"end":{"line":4,"column":1}},"children":[{"type":"text","value":"OpenViSUS is an open-source framework designed for efficient management, analysis, and visualization of large-scale scientific datasets. It enables interactive exploration of petabyte-scale data on a wide range of devices, from supercomputers to commodity laptops, making big data accessible to all users.","position":{"start":{"line":4,"column":1},"end":{"line":4,"column":1}},"key":"GSomHwJ0M1"}],"key":"M3vvDDfm6H"}],"key":"hadMzP5qm6"},{"type":"block","kind":"notebook-content","children":[{"type":"heading","depth":3,"position":{"start":{"line":2,"column":1},"end":{"line":2,"column":1}},"children":[{"type":"text","value":"Key Features","position":{"start":{"line":2,"column":1},"end":{"line":2,"column":1}},"key":"uza92Qo5TX"}],"identifier":"key-features","label":"Key Features","html_id":"key-features","implicit":true,"key":"inbchLaIK0"},{"type":"list","ordered":false,"spread":false,"position":{"start":{"line":3,"column":1},"end":{"line":7,"column":1}},"children":[{"type":"listItem","spread":true,"position":{"start":{"line":3,"column":1},"end":{"line":3,"column":1}},"children":[{"type":"paragraph","children":[{"type":"strong","position":{"start":{"line":3,"column":1},"end":{"line":3,"column":1}},"children":[{"type":"text","value":"Efficient Data Storage:","position":{"start":{"line":3,"column":1},"end":{"line":3,"column":1}},"key":"skyZGbsFz9"}],"key":"OUIseG7XNI"},{"type":"text","value":" Uses the IDX format, which stores data in a hierarchical Z (HZ) order for cache-oblivious, progressive access.","position":{"start":{"line":3,"column":1},"end":{"line":3,"column":1}},"key":"JCTalaegl5"}],"key":"Dx1DV4ZK74"}],"key":"tSfRO9T71g"},{"type":"listItem","spread":true,"position":{"start":{"line":4,"column":1},"end":{"line":4,"column":1}},"children":[{"type":"paragraph","children":[{"type":"strong","position":{"start":{"line":4,"column":1},"end":{"line":4,"column":1}},"children":[{"type":"text","value":"Scalable Visualization:","position":{"start":{"line":4,"column":1},"end":{"line":4,"column":1}},"key":"HIPiXjiAsT"}],"key":"FpR1TL9g9t"},{"type":"text","value":" Enables interactive visualization of terabyte and petabyte datasets without requiring high-end hardware.","position":{"start":{"line":4,"column":1},"end":{"line":4,"column":1}},"key":"qXe0nywRGG"}],"key":"gRd4RpdbbT"}],"key":"LLas9azV43"},{"type":"listItem","spread":true,"position":{"start":{"line":5,"column":1},"end":{"line":5,"column":1}},"children":[{"type":"paragraph","children":[{"type":"strong","position":{"start":{"line":5,"column":1},"end":{"line":5,"column":1}},"children":[{"type":"text","value":"Progressive Streaming:","position":{"start":{"line":5,"column":1},"end":{"line":5,"column":1}},"key":"PyUwupGyDx"}],"key":"bB7lHZqgsd"},{"type":"text","value":" Optimizes network utilization with state-of-the-art compression algorithms for fast data delivery and streaming.","position":{"start":{"line":5,"column":1},"end":{"line":5,"column":1}},"key":"QThkLpHdj3"}],"key":"S68d3etgBa"}],"key":"XE65WwTu6H"},{"type":"listItem","spread":true,"position":{"start":{"line":6,"column":1},"end":{"line":6,"column":1}},"children":[{"type":"paragraph","children":[{"type":"strong","position":{"start":{"line":6,"column":1},"end":{"line":6,"column":1}},"children":[{"type":"text","value":"Web-Based Dashboards:","position":{"start":{"line":6,"column":1},"end":{"line":6,"column":1}},"key":"oxLV4C5cyI"}],"key":"Ort0Bg1yBA"},{"type":"text","value":" Provides customizable dashboards for data analysis accessible from any device with an internet connection.","position":{"start":{"line":6,"column":1},"end":{"line":6,"column":1}},"key":"l0JMo9iHOe"}],"key":"tadiODMOQz"}],"key":"pmmgIn571v"},{"type":"listItem","spread":true,"position":{"start":{"line":7,"column":1},"end":{"line":7,"column":1}},"children":[{"type":"paragraph","children":[{"type":"strong","position":{"start":{"line":7,"column":1},"end":{"line":7,"column":1}},"children":[{"type":"text","value":"Open Source:","position":{"start":{"line":7,"column":1},"end":{"line":7,"column":1}},"key":"SnlAvZaIRq"}],"key":"i28zz5d9ZX"},{"type":"text","value":" Distributed under the permissive BSD license.","position":{"start":{"line":7,"column":1},"end":{"line":7,"column":1}},"key":"r7k0tEdF6z"}],"key":"MBMuXucEnr"}],"key":"oP88cQu1US"}],"key":"Z7GQKGV6Xj"}],"key":"TQhUPXNqc8"},{"type":"block","kind":"notebook-content","children":[{"type":"heading","depth":3,"position":{"start":{"line":1,"column":1},"end":{"line":1,"column":1}},"children":[{"type":"text","value":"Data Storage: The IDX Format","position":{"start":{"line":1,"column":1},"end":{"line":1,"column":1}},"key":"ICWukBfpSe"}],"identifier":"data-storage-the-idx-format","label":"Data Storage: The IDX Format","html_id":"data-storage-the-idx-format","implicit":true,"key":"RcyMaxyXVO"},{"type":"list","ordered":false,"spread":false,"position":{"start":{"line":2,"column":1},"end":{"line":3,"column":1}},"children":[{"type":"listItem","spread":true,"position":{"start":{"line":2,"column":1},"end":{"line":2,"column":1}},"children":[{"type":"paragraph","children":[{"type":"strong","position":{"start":{"line":2,"column":1},"end":{"line":2,"column":1}},"children":[{"type":"text","value":"Hierarchical Z (HZ) Order:","position":{"start":{"line":2,"column":1},"end":{"line":2,"column":1}},"key":"ALymfOo8IB"}],"key":"BV2ZcZIZtM"},{"type":"text","value":" Data is organized to allow efficient, multi-resolution access and visualization.","position":{"start":{"line":2,"column":1},"end":{"line":2,"column":1}},"key":"e4ZY4SoR2j"}],"key":"NGwU90u6T3"}],"key":"DCxOyi4rEf"},{"type":"listItem","spread":true,"position":{"start":{"line":3,"column":1},"end":{"line":3,"column":1}},"children":[{"type":"paragraph","children":[{"type":"strong","position":{"start":{"line":3,"column":1},"end":{"line":3,"column":1}},"children":[{"type":"text","value":"Progressive Access:","position":{"start":{"line":3,"column":1},"end":{"line":3,"column":1}},"key":"xmGglWMGTh"}],"key":"nyTdhsTTyl"},{"type":"text","value":" Users can interactively explore data at different resolutions, starting with coarse overviews and refining to full detail as needed.","position":{"start":{"line":3,"column":1},"end":{"line":3,"column":1}},"key":"FWw8n3hdDU"}],"key":"nr8gX4xBFL"}],"key":"wfBlmbm1q3"}],"key":"rb6fTSIp4n"}],"key":"JsiN0Gy0Kr"},{"type":"block","kind":"notebook-content","children":[{"type":"heading","depth":3,"position":{"start":{"line":1,"column":1},"end":{"line":1,"column":1}},"children":[{"type":"text","value":"Data Delivery","position":{"start":{"line":1,"column":1},"end":{"line":1,"column":1}},"key":"nfpryWL7Pg"}],"identifier":"data-delivery","label":"Data Delivery","html_id":"data-delivery","implicit":true,"key":"kPYVCJ694M"},{"type":"list","ordered":false,"spread":false,"position":{"start":{"line":2,"column":1},"end":{"line":3,"column":1}},"children":[{"type":"listItem","spread":true,"position":{"start":{"line":2,"column":1},"end":{"line":2,"column":1}},"children":[{"type":"paragraph","children":[{"type":"strong","position":{"start":{"line":2,"column":1},"end":{"line":2,"column":1}},"children":[{"type":"text","value":"Interactive Streaming:","position":{"start":{"line":2,"column":1},"end":{"line":2,"column":1}},"key":"heewkq6WtH"}],"key":"gQmm1WSFJ6"},{"type":"text","value":" Share and stream large datasets using simple server modules (e.g., Apache), enabling teravoxel imagery delivery.","position":{"start":{"line":2,"column":1},"end":{"line":2,"column":1}},"key":"Et7XCGvFtw"}],"key":"vG24nPSNXP"}],"key":"KEfUXJHEzU"},{"type":"listItem","spread":true,"position":{"start":{"line":3,"column":1},"end":{"line":3,"column":1}},"children":[{"type":"paragraph","children":[{"type":"strong","position":{"start":{"line":3,"column":1},"end":{"line":3,"column":1}},"children":[{"type":"text","value":"Cloud and Local Access:","position":{"start":{"line":3,"column":1},"end":{"line":3,"column":1}},"key":"S9hDOi5lv7"}],"key":"WfUUG210PI"},{"type":"text","value":" Data can be accessed from local storage or cloud repositories, with optimized streaming for remote analysis.","position":{"start":{"line":3,"column":1},"end":{"line":3,"column":1}},"key":"yH3byUO30o"}],"key":"nqQq0EC6jt"}],"key":"DXd0JBszNQ"}],"key":"mDLOIphFjW"}],"key":"lTVsA3Vo9H"},{"type":"block","kind":"notebook-content","children":[{"type":"heading","depth":3,"position":{"start":{"line":1,"column":1},"end":{"line":1,"column":1}},"children":[{"type":"text","value":"Interactive Analysis and Visualization","position":{"start":{"line":1,"column":1},"end":{"line":1,"column":1}},"key":"uq23QSYcKi"}],"identifier":"interactive-analysis-and-visualization","label":"Interactive Analysis and Visualization","html_id":"interactive-analysis-and-visualization","implicit":true,"key":"vhkGBdDb26"},{"type":"list","ordered":false,"spread":false,"position":{"start":{"line":2,"column":1},"end":{"line":5,"column":1}},"children":[{"type":"listItem","spread":true,"position":{"start":{"line":2,"column":1},"end":{"line":2,"column":1}},"children":[{"type":"paragraph","children":[{"type":"strong","position":{"start":{"line":2,"column":1},"end":{"line":2,"column":1}},"children":[{"type":"text","value":"Cross-Platform:","position":{"start":{"line":2,"column":1},"end":{"line":2,"column":1}},"key":"fdw8YYzfTd"}],"key":"u7TBtsGAOy"},{"type":"text","value":" Works on supercomputers, desktops, and laptops.","position":{"start":{"line":2,"column":1},"end":{"line":2,"column":1}},"key":"p4suiQ8tj7"}],"key":"wG8FLsPsZq"}],"key":"UiXkCHnwfY"},{"type":"listItem","spread":true,"position":{"start":{"line":3,"column":1},"end":{"line":3,"column":1}},"children":[{"type":"paragraph","children":[{"type":"strong","position":{"start":{"line":3,"column":1},"end":{"line":3,"column":1}},"children":[{"type":"text","value":"Scripting Support:","position":{"start":{"line":3,"column":1},"end":{"line":3,"column":1}},"key":"S4xQnAAKuO"}],"key":"vp1Hr9FobN"},{"type":"text","value":" Experiment with interactive scripting for rapid data insights.","position":{"start":{"line":3,"column":1},"end":{"line":3,"column":1}},"key":"V8FkrEN93Q"}],"key":"SUGKj5wSfR"}],"key":"YhVTon6xZB"},{"type":"listItem","spread":true,"position":{"start":{"line":4,"column":1},"end":{"line":5,"column":1}},"children":[{"type":"paragraph","children":[{"type":"strong","position":{"start":{"line":4,"column":1},"end":{"line":4,"column":1}},"children":[{"type":"text","value":"User-Friendly Querying:","position":{"start":{"line":4,"column":1},"end":{"line":4,"column":1}},"key":"u80bx4vZuj"}],"key":"i55HgB24HH"},{"type":"text","value":" Abstracts complexities of file systems and cloud services, allowing scientists to focus on analysis.","position":{"start":{"line":4,"column":1},"end":{"line":4,"column":1}},"key":"FSpScGLAKB"}],"key":"yNGeGqsRNz"}],"key":"MLtRxmeYdX"}],"key":"yhpSl9ypUs"}],"key":"tTgtsvMVjx"},{"type":"block","kind":"notebook-content","children":[{"type":"heading","depth":3,"position":{"start":{"line":1,"column":1},"end":{"line":1,"column":1}},"children":[{"type":"text","value":"2026 IEEE SciVis  Contest","position":{"start":{"line":1,"column":1},"end":{"line":1,"column":1}},"key":"zo5hv7CLgT"}],"identifier":"id-2026-ieee-scivis-contest","label":"2026 IEEE SciVis  Contest","html_id":"id-2026-ieee-scivis-contest","implicit":true,"key":"GzgixaoGYi"},{"type":"paragraph","position":{"start":{"line":3,"column":1},"end":{"line":3,"column":1}},"children":[{"type":"text","value":"NSDF-OpenVISUS is directly supporting the 2026 IEEE SciVis Contest. This contest is held annually as part of the IEEE VIS Conference. In 2026, this contest will focus on the visualization of petascale oceanic and atmospheric climate data provided by NASA. This year’s challenge emphasizes advanced visualization methods for exploring vast climate datasets, encouraging innovative solutions that address real-world issues such as climate prediction, weather simulation, and environmental impact analysis.","position":{"start":{"line":3,"column":1},"end":{"line":3,"column":1}},"key":"bzS30dWClR"}],"key":"wZZXZsklja"},{"type":"paragraph","position":{"start":{"line":6,"column":1},"end":{"line":6,"column":1}},"children":[{"type":"text","value":"The best submission wins $1000 cash prize. Find more information on the official ","position":{"start":{"line":6,"column":1},"end":{"line":6,"column":1}},"key":"zFSo0SnO4E"},{"type":"link","url":"https://sciviscontest2026.github.io/","children":[{"type":"text","value":"SciVis website","key":"jrgJglL6vs"}],"urlSource":"https://sciviscontest2026.github.io/","key":"XALpfTy8jP"},{"type":"text","value":".","position":{"start":{"line":6,"column":1},"end":{"line":6,"column":1}},"key":"qznWjenDSU"}],"key":"zFXMgfQBAI"}],"key":"GF6p2peRz0"},{"type":"block","kind":"notebook-content","children":[{"type":"heading","depth":3,"position":{"start":{"line":1,"column":1},"end":{"line":1,"column":1}},"children":[{"type":"text","value":"Example Use Cases","position":{"start":{"line":1,"column":1},"end":{"line":1,"column":1}},"key":"LpMME8B1pA"}],"identifier":"example-use-cases","label":"Example Use Cases","html_id":"example-use-cases","implicit":true,"key":"UPOYkPEgTF"},{"type":"list","ordered":false,"spread":false,"position":{"start":{"line":2,"column":1},"end":{"line":4,"column":1}},"children":[{"type":"listItem","spread":true,"position":{"start":{"line":2,"column":1},"end":{"line":2,"column":1}},"children":[{"type":"paragraph","children":[{"type":"link","url":"https://chpc3.nationalsciencedatafabric.org:11957/dashboards","children":[{"type":"text","value":"NASA LLC2160 Data Interactive Dashboard","key":"UhVl1fEbnv"}],"urlSource":"https://chpc3.nationalsciencedatafabric.org:11957/dashboards","key":"Y2VAnWAr9Z"}],"key":"fFOI1FhqCk"}],"key":"dzgNRsl1kj"},{"type":"listItem","spread":true,"position":{"start":{"line":3,"column":1},"end":{"line":3,"column":1}},"children":[{"type":"paragraph","children":[{"type":"link","url":"https://nasa-arset.nationalsciencedatafabric.org","children":[{"type":"text","value":"NEX-GDDP-CMIP6 Dashboard","key":"FUQvLFergn"}],"urlSource":"https://nasa-arset.nationalsciencedatafabric.org","key":"lXD3poTn2O"}],"key":"VDGH4LhkdP"}],"key":"Tulda1y6KH"},{"type":"listItem","spread":true,"position":{"start":{"line":4,"column":1},"end":{"line":4,"column":1}},"children":[{"type":"paragraph","children":[{"type":"text","value":"Classroom deployment for minority-serving institutions","position":{"start":{"line":4,"column":1},"end":{"line":4,"column":1}},"key":"GTI2okgqUU"}],"key":"mrGIcL8q0u"}],"key":"wkJfYMYq2X"}],"key":"z9bfZnHtfY"}],"key":"u9dKo9MtJr"},{"type":"block","kind":"notebook-content","children":[{"type":"heading","depth":3,"position":{"start":{"line":1,"column":1},"end":{"line":1,"column":1}},"children":[{"type":"text","value":"Other Deplyments","position":{"start":{"line":1,"column":1},"end":{"line":1,"column":1}},"key":"gyw52abp2a"}],"identifier":"other-deplyments","label":"Other Deplyments","html_id":"other-deplyments","implicit":true,"key":"UWtxqrrv0x"},{"type":"list","ordered":true,"start":1,"spread":false,"position":{"start":{"line":2,"column":1},"end":{"line":5,"column":1}},"children":[{"type":"listItem","spread":true,"position":{"start":{"line":2,"column":1},"end":{"line":2,"column":1}},"children":[{"type":"paragraph","children":[{"type":"link","url":"https://www.chess.cornell.edu/national-science-data-fabric-and-chess-collaborate-democratize-data-driven-scientific-discovery","children":[{"type":"text","value":"Cornell High Energy Synchrotron Source (CHESS)","key":"rc2xCaS3QE"}],"urlSource":"https://www.chess.cornell.edu/national-science-data-fabric-and-chess-collaborate-democratize-data-driven-scientific-discovery","key":"rIEpLYNpo2"}],"key":"eku1LIwaxH"}],"key":"jh5iZ4fUvn"},{"type":"listItem","spread":true,"position":{"start":{"line":3,"column":1},"end":{"line":3,"column":1}},"children":[{"type":"paragraph","children":[{"type":"link","url":"https://ncar.nationalsciencedatafabric.org/neon-demo/v1","children":[{"type":"text","value":"National Center for Atmospheric Research (NCAR)","key":"kOwMMWVhv5"}],"urlSource":"https://ncar.nationalsciencedatafabric.org/neon-demo/v1","key":"lFo5KkPFou"}],"key":"FQsT3sqlJQ"}],"key":"mEHU84fykp"},{"type":"listItem","spread":true,"position":{"start":{"line":4,"column":1},"end":{"line":4,"column":1}},"children":[{"type":"paragraph","children":[{"type":"link","url":"https://data.neonscience.org/data-products/DP3.30010.001","children":[{"type":"text","value":"NEON","key":"HwkqPEWUt5"}],"urlSource":"https://data.neonscience.org/data-products/DP3.30010.001","key":"En0DV8PHFm"}],"key":"u2ZaUQxbJt"}],"key":"lYXN3CE40t"},{"type":"listItem","spread":true,"position":{"start":{"line":5,"column":1},"end":{"line":5,"column":1}},"children":[{"type":"paragraph","children":[{"type":"link","url":"https://chpc3.nationalsciencedatafabric.org:8989/dashboards","children":[{"type":"text","value":"SOMOSPIE","key":"vLd95b10rw"}],"urlSource":"https://chpc3.nationalsciencedatafabric.org:8989/dashboards","key":"j5N9Gtbs9p"}],"key":"NbIqUKL2MZ"}],"key":"wmUoVkoVTB"}],"key":"ZDhoKNrxTg"}],"key":"eyY3sDZjt8"},{"type":"block","kind":"notebook-content","children":[{"type":"heading","depth":3,"position":{"start":{"line":2,"column":1},"end":{"line":2,"column":1}},"children":[{"type":"text","value":"Getting Started","position":{"start":{"line":2,"column":1},"end":{"line":2,"column":1}},"key":"QdDPZZCELE"}],"identifier":"getting-started","label":"Getting Started","html_id":"getting-started","implicit":true,"key":"ZLZOndOoXT"},{"type":"heading","depth":4,"position":{"start":{"line":3,"column":1},"end":{"line":3,"column":1}},"children":[{"type":"text","value":"Installation","position":{"start":{"line":3,"column":1},"end":{"line":3,"column":1}},"key":"DlIHwqmvfz"}],"identifier":"installation","label":"Installation","html_id":"installation","implicit":true,"key":"sCibosEtaQ"},{"type":"list","ordered":true,"start":1,"spread":false,"position":{"start":{"line":4,"column":1},"end":{"line":8,"column":1}},"children":[{"type":"listItem","spread":true,"position":{"start":{"line":4,"column":1},"end":{"line":5,"column":1}},"children":[{"type":"paragraph","children":[{"type":"strong","position":{"start":{"line":4,"column":1},"end":{"line":4,"column":1}},"children":[{"type":"text","value":"Install Using ","position":{"start":{"line":4,"column":1},"end":{"line":4,"column":1}},"key":"rRBsBLDZcw"},{"type":"inlineCode","value":"pip","position":{"start":{"line":4,"column":1},"end":{"line":4,"column":1}},"key":"ZgJUY3zMxi"}],"key":"wQP7mta25l"}],"key":"rH6IXb5VjJ"},{"type":"list","ordered":false,"spread":false,"position":{"start":{"line":5,"column":1},"end":{"line":5,"column":1}},"children":[{"type":"listItem","spread":true,"position":{"start":{"line":5,"column":1},"end":{"line":5,"column":1}},"children":[{"type":"paragraph","children":[{"type":"inlineCode","value":"pip install OpenVisus","position":{"start":{"line":5,"column":1},"end":{"line":5,"column":1}},"key":"K1E7qVAX6E"}],"key":"h3t8ag8Ai5"}],"key":"jGXZ6QNifz"}],"key":"GJmx93o6kJ"}],"key":"frh8av1HoR"},{"type":"listItem","spread":true,"position":{"start":{"line":6,"column":1},"end":{"line":8,"column":1}},"children":[{"type":"paragraph","children":[{"type":"strong","position":{"start":{"line":6,"column":1},"end":{"line":6,"column":1}},"children":[{"type":"text","value":"Build from Source:","position":{"start":{"line":6,"column":1},"end":{"line":6,"column":1}},"key":"OMCYnprALK"}],"key":"X0Ego3b7Us"}],"key":"RDIVCLZOeW"},{"type":"list","ordered":false,"spread":false,"position":{"start":{"line":7,"column":1},"end":{"line":8,"column":1}},"children":[{"type":"listItem","spread":true,"position":{"start":{"line":7,"column":1},"end":{"line":7,"column":1}},"children":[{"type":"paragraph","children":[{"type":"text","value":"Clone the repository: ","position":{"start":{"line":7,"column":1},"end":{"line":7,"column":1}},"key":"tXBihUssVe"},{"type":"inlineCode","value":"git clone https://github.com/sci-visus/OpenVisus.git","position":{"start":{"line":7,"column":1},"end":{"line":7,"column":1}},"key":"oVd8eEmxfs"}],"key":"C7bRcCJ2ec"}],"key":"ke3pFdRjWJ"},{"type":"listItem","spread":true,"position":{"start":{"line":8,"column":1},"end":{"line":8,"column":1}},"children":[{"type":"paragraph","children":[{"type":"text","value":"Follow instructions in the ","position":{"start":{"line":8,"column":1},"end":{"line":8,"column":1}},"key":"UTL566srdN"},{"type":"inlineCode","value":"README.md","position":{"start":{"line":8,"column":1},"end":{"line":8,"column":1}},"key":"vwGWil6MyZ"},{"type":"text","value":" and ","position":{"start":{"line":8,"column":1},"end":{"line":8,"column":1}},"key":"IlOWSLrMf4"},{"type":"inlineCode","value":"docs/compilation.md","position":{"start":{"line":8,"column":1},"end":{"line":8,"column":1}},"key":"LUQB8P10iC"},{"type":"text","value":" for building on your platform.","position":{"start":{"line":8,"column":1},"end":{"line":8,"column":1}},"key":"Df8tmbtATQ"}],"key":"bYqkOPNTlI"}],"key":"rYfnIYgj4N"}],"key":"lTtxyeTc4O"}],"key":"JNbRVd1dCC"}],"key":"b1BbJGadui"}],"key":"Am1HhxOztk"},{"type":"block","kind":"notebook-content","children":[{"type":"heading","depth":3,"position":{"start":{"line":2,"column":1},"end":{"line":2,"column":1}},"children":[{"type":"text","value":"References","position":{"start":{"line":2,"column":1},"end":{"line":2,"column":1}},"key":"N8OjfUpucm"}],"identifier":"references","label":"References","html_id":"references","implicit":true,"key":"fgTxtqpVWj"},{"type":"list","ordered":false,"spread":false,"position":{"start":{"line":3,"column":1},"end":{"line":6,"column":1}},"children":[{"type":"listItem","spread":true,"position":{"start":{"line":3,"column":1},"end":{"line":3,"column":1}},"children":[{"type":"paragraph","children":[{"type":"link","url":"https://nationalsciencedatafabric.org/","children":[{"type":"text","value":"National Science Data Fabric","key":"z3ICO9jeda"}],"urlSource":"https://nationalsciencedatafabric.org/","key":"IyPmmjItnV"}],"key":"UGxyvnfi9i"}],"key":"rxGwtlShCI"},{"type":"listItem","spread":true,"position":{"start":{"line":4,"column":1},"end":{"line":4,"column":1}},"children":[{"type":"paragraph","children":[{"type":"link","url":"https://github.com/sci-visus/OpenVisus","children":[{"type":"text","value":"OpenVisus","key":"jfanTakoYV"}],"urlSource":"https://github.com/sci-visus/OpenVisus","error":true,"key":"NhJlWHlqjw"}],"key":"G146IGwDJ5"}],"key":"Tb1elJcsQi"},{"type":"listItem","spread":true,"position":{"start":{"line":5,"column":1},"end":{"line":6,"column":1}},"children":[{"type":"paragraph","children":[{"type":"link","url":"https://github.com/sci-visus/OpenVisuspy","children":[{"type":"text","value":"OpenVisuspy","key":"ftRHqVBogN"}],"urlSource":"https://github.com/sci-visus/OpenVisuspy","error":true,"key":"ou2dsz220P"}],"key":"SqsrHwJ2St"}],"key":"jYscTDCiZV"}],"key":"cESNbCQeaE"},{"type":"thematicBreak","position":{"start":{"line":7,"column":1},"end":{"line":7,"column":1}},"key":"ytdujI4SgQ"},{"type":"paragraph","position":{"start":{"line":8,"column":1},"end":{"line":8,"column":1}},"children":[{"type":"text","value":"Please consult these papers for technical details and use cases:","position":{"start":{"line":8,"column":1},"end":{"line":8,"column":1}},"key":"XHuQNKOqes"}],"key":"qrQfz9mHy4"},{"type":"list","ordered":false,"spread":false,"position":{"start":{"line":10,"column":1},"end":{"line":12,"column":1}},"children":[{"type":"listItem","spread":true,"position":{"start":{"line":10,"column":1},"end":{"line":10,"column":1}},"children":[{"type":"paragraph","children":[{"type":"link","url":"https://arxiv.org/abs/2408.11831v1","children":[{"type":"text","value":"Web-based Visualization and Analytics of Petascale data: Equity as a Tide that Lifts All Boats","key":"S0FasdqqkJ"}],"urlSource":"https://arxiv.org/abs/2408.11831v1","key":"GGGHYma2tc"}],"key":"NyyKNiaHCd"}],"key":"MK6XGrprje"},{"type":"listItem","spread":true,"position":{"start":{"line":11,"column":1},"end":{"line":11,"column":1}},"children":[{"type":"paragraph","children":[{"type":"link","url":"https://arxiv.org/abs/2009.03254","children":[{"type":"text","value":"Interactive Visualization of Terascale Data in the Browser: Fact or Fiction?","key":"FxRhuQCFqI"}],"urlSource":"https://arxiv.org/abs/2009.03254","key":"SGOsCodrMe"}],"key":"PowxoH1bvx"}],"key":"NNCbZ8Pjgr"},{"type":"listItem","spread":true,"position":{"start":{"line":12,"column":1},"end":{"line":12,"column":1}},"children":[{"type":"paragraph","children":[{"type":"link","url":"https://sci.utah.edu/publications/Kum2014a/KumarISC2014.pdf","children":[{"type":"text","value":"Fast Multiresolution Reads of Massive Simulation Datasets","key":"ta9WOegzyA"}],"urlSource":"https://sci.utah.edu/publications/Kum2014a/KumarISC2014.pdf","key":"Og8Da0QCKG"}],"key":"SqImHr76ex"}],"key":"EUXMo4j5kn"}],"key":"dOJRlv9E5H"}],"key":"UVMoNAd98l"},{"type":"block","kind":"notebook-content","children":[{"type":"heading","depth":4,"position":{"start":{"line":1,"column":1},"end":{"line":1,"column":1}},"children":[{"type":"emphasis","position":{"start":{"line":1,"column":1},"end":{"line":1,"column":1}},"children":[{"type":"text","value":"Please reach out to Aashish Panta, Giorgio Scorzelli or Valerio Pascucci for any concerns about the notebook. Thank you!","position":{"start":{"line":1,"column":1},"end":{"line":1,"column":1}},"key":"ZgXKlyshqt"}],"key":"fc0jcAwn2d"}],"identifier":"please-reach-out-to-aashish-panta-giorgio-scorzelli-or-valerio-pascucci-for-any-concerns-about-the-notebook-thank-you","label":"Please reach out to Aashish Panta, Giorgio Scorzelli or Valerio Pascucci for any concerns about the notebook. Thank you!","html_id":"please-reach-out-to-aashish-panta-giorgio-scorzelli-or-valerio-pascucci-for-any-concerns-about-the-notebook-thank-you","implicit":true,"key":"qjqr6MenSd"},{"type":"list","ordered":false,"spread":false,"position":{"start":{"line":2,"column":1},"end":{"line":4,"column":1}},"children":[{"type":"listItem","spread":true,"position":{"start":{"line":2,"column":1},"end":{"line":2,"column":1}},"children":[{"type":"paragraph","children":[{"type":"text","value":"Aashish Panta (","position":{"start":{"line":2,"column":1},"end":{"line":2,"column":1}},"key":"XDEdeUPOM8"},{"type":"link","url":"mailto:aashishpanta0@gmail.com","position":{"start":{"line":2,"column":1},"end":{"line":2,"column":1}},"children":[{"type":"text","value":"aashishpanta0@gmail​.com","position":{"start":{"line":2,"column":1},"end":{"line":2,"column":1}},"key":"lNgloH40HJ"}],"urlSource":"mailto:aashishpanta0@gmail.com","key":"eDfKYytQXf"},{"type":"text","value":")","position":{"start":{"line":2,"column":1},"end":{"line":2,"column":1}},"key":"Prb960BIyk"}],"key":"Bti3fYWYqF"}],"key":"PCLXV6e1RT"},{"type":"listItem","spread":true,"position":{"start":{"line":3,"column":1},"end":{"line":3,"column":1}},"children":[{"type":"paragraph","children":[{"type":"text","value":"Giorgio Scorzelli (","position":{"start":{"line":3,"column":1},"end":{"line":3,"column":1}},"key":"UdJWcp0vpo"},{"type":"link","url":"mailto:scrgiorgio@gmail.com","position":{"start":{"line":3,"column":1},"end":{"line":3,"column":1}},"children":[{"type":"text","value":"scrgiorgio@gmail​.com","position":{"start":{"line":3,"column":1},"end":{"line":3,"column":1}},"key":"iXaULvQZ1n"}],"urlSource":"mailto:scrgiorgio@gmail.com","key":"gByJsdH9vX"},{"type":"text","value":")","position":{"start":{"line":3,"column":1},"end":{"line":3,"column":1}},"key":"j6ACP2Kf3S"}],"key":"YYHBdFO2gy"}],"key":"gRW0zJIvor"},{"type":"listItem","spread":true,"position":{"start":{"line":4,"column":1},"end":{"line":4,"column":1}},"children":[{"type":"paragraph","children":[{"type":"text","value":"Valerio Pascucci (","position":{"start":{"line":4,"column":1},"end":{"line":4,"column":1}},"key":"DLspN2Hn4l"},{"type":"link","url":"mailto:pascucci.valerio@gmail.com","position":{"start":{"line":4,"column":1},"end":{"line":4,"column":1}},"children":[{"type":"text","value":"pascucci​.valerio@gmail​.com","position":{"start":{"line":4,"column":1},"end":{"line":4,"column":1}},"key":"jWX2GErCYh"}],"urlSource":"mailto:pascucci.valerio@gmail.com","key":"WULqFS6nJN"},{"type":"text","value":")","position":{"start":{"line":4,"column":1},"end":{"line":4,"column":1}},"key":"aGbFlgma5C"}],"key":"u4guKYfTTa"}],"key":"HTyzf6nM71"}],"key":"MHBxQ21NS7"}],"key":"vAj9wIDWwD"},{"type":"block","kind":"notebook-content","children":[{"type":"thematicBreak","position":{"start":{"line":1,"column":1},"end":{"line":1,"column":1}},"key":"IwBrAUgWMI"}],"key":"SNK3oo3Vkj"}],"key":"tShKx0wlXA"},"references":{"cite":{"order":[],"data":{}}},"footer":{"navigation":{"prev":{"title":"How to Cite This Cookbook","url":"/notebooks/how-to-cite","group":"Preamble"},"next":{"title":"DYAMOND LLC2160 Atmospheric Dataset Notebook","url":"/notebooks/atmosphere-llc2160-visualization","group":"NASA DYAMOND Datasets (C1440-LLC2160)"}}},"domain":"http://localhost:3000"}